ptbtest/__init__.py
ptbtest/callbackquerygenerator.py
ptbtest/chatgenerator.py
ptbtest/entityparser.py
ptbtest/errors.py
ptbtest/inlinequerygenerator.py
ptbtest/messagegenerator.py
ptbtest/mockbot.py
ptbtest/ptbgenerator.py
ptbtest/updategenerator.py
ptbtest/usergenerator.py
ptb_unittest-1.1.1.dist-info/LICENSE
ptb_unittest-1.1.1.dist-info/LICENSE.lesser
ptb_unittest-1.1.1.dist-info/METADATA
ptb_unittest-1.1.1.dist-info/WHEEL
ptb_unittest-1.1.1.dist-info/top_level.txt
ptb_unittest-1.1.1.dist-info/RECORD
