Metadata-Version: 2.1
Name: ptb-unittest
Version: 1.1.1
Summary: A test suite for use with python-telegram-bot
Home-page: https://github.com/GauthamramRavichandran/ptbtest
Author: Gauthamram Ravichandran
Author-email: gauthamram.ravichandran@protonmail.com
License: GNU General Public License v3.0
Keywords: python telegram bot unittest
Platform: UNKNOWN
Classifier: Development Status :: 5 - Production/Stable
Classifier: Intended Audience :: Developers
Classifier: License :: OSI Approved :: GNU Lesser General Public License v3 (LGPLv3)
Classifier: Operating System :: OS Independent
Classifier: Topic :: Software Development :: Libraries :: Python Modules
Classifier: Topic :: Software Development :: Testing
Classifier: Topic :: Internet
Classifier: Programming Language :: Python
Classifier: Programming Language :: Python :: 3
Classifier: Programming Language :: Python :: 3.3
Classifier: Programming Language :: Python :: 3.4
Classifier: Programming Language :: Python :: 3.5
Classifier: Programming Language :: Python :: 3.6
License-File: LICENSE
License-File: LICENSE.lesser
Requires-Dist: python-telegram-bot
